geometry/__init__.py
geometry/patch.py
geometry/sample.py
geometry/spherical_to_cartesian.py
geometry/vector_generator.py
PBHnbody-0.0.1.dist-info/LICENSE
PBHnbody-0.0.1.dist-info/METADATA
PBHnbody-0.0.1.dist-info/WHEEL
PBHnbody-0.0.1.dist-info/top_level.txt
PBHnbody-0.0.1.dist-info/RECORD
