Metadata-Version: 2.1
Name: PBHnbody
Version: 0.0.1
Summary: Nbody simulation necessities
Home-page: https://github.com/oross/nbody
Author: Olivia Ross
Author-email: oross@ucsc.edu
License: UNKNOWN
Platform: UNKNOWN
Classifier: Programming Language :: Python :: 3
Classifier: License :: OSI Approved :: MIT License
Classifier: Operating System :: OS Independent
Requires-Python: >=3.6
